esxi_img/__init__.py
esxi_img/cmd.py
esxi_img/tarball.py
esxi_img/data/README.md
esxi_img/data/__init__.py
esxi_img/data/ks-template.cfg
esxi_img/data/firstboot/40-network.sh
esxi_img/data/firstboot/98-reboot.sh
esxi_img/data/post/10-configdrive-module.sh
esxi_img/data/post/15-netinit-module.sh
esxi_img/data/pre/10-fix-disks.sh
esxi_img/data/pre/12-mount-configdrive.sh
esxi_img/data/pre/15-set-root-passwd.py
esxi_img/data/pre/90-umount-configdrive.sh
esxi_img-0.1.3.dist-info/METADATA
esxi_img-0.1.3.dist-info/WHEEL
esxi_img-0.1.3.dist-info/entry_points.txt
esxi_img-0.1.3.dist-info/licenses/LICENSE
esxi_img-0.1.3.dist-info/RECORD
