Metadata-Version: 2.4
Name: esxi-img
Version: 0.1.3
Summary: ESXi installer image generator
Project-URL: Homepage, https://github.com/rackerlabs/esxi-img
Project-URL: Issues, https://github.com/rackerlabs/esxi-img/issues
Author-email: Doug Goldstein <Doug.Goldstein@rackspace.com>, Marek Skrobacki <marek.skrobacki@rackspace.co.uk>
License: Apache-2.0
License-File: LICENSE
Requires-Python: >=3.11
Requires-Dist: esxi-netinit>=0.1.0
Requires-Dist: pycdlib>=1.14.0
